<annotation>
	<folder>2</folder>
	<filename>ezgif-frame-098.jpg</filename>
	<path>D:\Tugas\Kuliah_Semester_VII\ProDs2\Data\Gambar\2\ezgif-frame-098.jpg</path>
	<source>
		<database>Unknown</database>
	</source>
	<size>
		<width>960</width>
		<height>540</height>
		<depth>3</depth>
	</size>
	<segmented>0</segmented>
	<object>
		<name>mobil</name>
		<pose>Unspecified</pose>
		<truncated>0</truncated>
		<difficult>0</difficult>
		<bndbox>
			<xmin>722</xmin>
			<ymin>315</ymin>
			<xmax>879</xmax>
			<ymax>469</ymax>
		</bndbox>
	</object>
	<object>
		<name>mobil</name>
		<pose>Unspecified</pose>
		<truncated>0</truncated>
		<difficult>0</difficult>
		<bndbox>
			<xmin>375</xmin>
			<ymin>159</ymin>
			<xmax>476</xmax>
			<ymax>275</ymax>
		</bndbox>
	</object>
	<object>
		<name>mobil</name>
		<pose>Unspecified</pose>
		<truncated>0</truncated>
		<difficult>0</difficult>
		<bndbox>
			<xmin>232</xmin>
			<ymin>108</ymin>
			<xmax>321</xmax>
			<ymax>194</ymax>
		</bndbox>
	</object>
	<object>
		<name>mobil</name>
		<pose>Unspecified</pose>
		<truncated>1</truncated>
		<difficult>0</difficult>
		<bndbox>
			<xmin>1</xmin>
			<ymin>127</ymin>
			<xmax>33</xmax>
			<ymax>205</ymax>
		</bndbox>
	</object>
	<object>
		<name>motor</name>
		<pose>Unspecified</pose>
		<truncated>0</truncated>
		<difficult>0</difficult>
		<bndbox>
			<xmin>319</xmin>
			<ymin>93</ymin>
			<xmax>345</xmax>
			<ymax>161</ymax>
		</bndbox>
	</object>
	<object>
		<name>motor</name>
		<pose>Unspecified</pose>
		<truncated>0</truncated>
		<difficult>0</difficult>
		<bndbox>
			<xmin>257</xmin>
			<ymin>52</ymin>
			<xmax>283</xmax>
			<ymax>101</ymax>
		</bndbox>
	</object>
	<object>
		<name>motor</name>
		<pose>Unspecified</pose>
		<truncated>0</truncated>
		<difficult>0</difficult>
		<bndbox>
			<xmin>206</xmin>
			<ymin>65</ymin>
			<xmax>224</xmax>
			<ymax>112</ymax>
		</bndbox>
	</object>
	<object>
		<name>motor</name>
		<pose>Unspecified</pose>
		<truncated>0</truncated>
		<difficult>0</difficult>
		<bndbox>
			<xmin>215</xmin>
			<ymin>42</ymin>
			<xmax>242</xmax>
			<ymax>92</ymax>
		</bndbox>
	</object>
	<object>
		<name>motor</name>
		<pose>Unspecified</pose>
		<truncated>0</truncated>
		<difficult>0</difficult>
		<bndbox>
			<xmin>195</xmin>
			<ymin>26</ymin>
			<xmax>211</xmax>
			<ymax>71</ymax>
		</bndbox>
	</object>
	<object>
		<name>motor</name>
		<pose>Unspecified</pose>
		<truncated>0</truncated>
		<difficult>0</difficult>
		<bndbox>
			<xmin>167</xmin>
			<ymin>29</ymin>
			<xmax>189</xmax>
			<ymax>89</ymax>
		</bndbox>
	</object>
	<object>
		<name>motor</name>
		<pose>Unspecified</pose>
		<truncated>0</truncated>
		<difficult>0</difficult>
		<bndbox>
			<xmin>131</xmin>
			<ymin>35</ymin>
			<xmax>158</xmax>
			<ymax>94</ymax>
		</bndbox>
	</object>
	<object>
		<name>motor</name>
		<pose>Unspecified</pose>
		<truncated>0</truncated>
		<difficult>0</difficult>
		<bndbox>
			<xmin>144</xmin>
			<ymin>13</ymin>
			<xmax>163</xmax>
			<ymax>64</ymax>
		</bndbox>
	</object>
</annotation>
